reflex_simple_password/__init__.py
reflex_simple_password/simple_password.py
reflex_simple_password-0.0.1.dist-info/METADATA
reflex_simple_password-0.0.1.dist-info/WHEEL
reflex_simple_password-0.0.1.dist-info/top_level.txt
reflex_simple_password-0.0.1.dist-info/RECORD
